README.md
setup.cfg
setup.py
integral_types/__init__.py
integral_types/byte.py
integral_types/errors.py
integral_types/int.py
integral_types/long.py
integral_types/longlong.py
integral_types/short.py
integral_types/ubyte.py
integral_types/uint.py
integral_types/ulong.py
integral_types/ulonglong.py
integral_types/ushort.py
integral_types.egg-info/PKG-INFO
integral_types.egg-info/SOURCES.txt
integral_types.egg-info/dependency_links.txt
integral_types.egg-info/top_level.txt