Metadata-Version: 1.0
Name: integral-types
Version: 1.1.1
Summary: A package supporting various C++-standard number types.
Home-page: https://github.com/HTG-YT/number-types
Author: Harry.
Author-email: harrywyt428@gmail.com
License: MIT
Platform: UNKNOWN
